autocar3g/AI.py
autocar3g/__init__.py
autocar3g/absclient.py
autocar3g/camera.py
autocar3g/driving.py
autocar3g/encoder.py
autocar3g/imu.py
autocar3g/led.py
autocar3g/lidar.py
autocar3g/ultrasonic.py
autocar3g-0.1.0.dist-info/METADATA
autocar3g-0.1.0.dist-info/WHEEL
autocar3g-0.1.0.dist-info/top_level.txt
autocar3g-0.1.0.dist-info/RECORD
