Metadata-Version: 2.4
Name: autocar3g
Version: 0.1.0
Summary: Pop plus library for Autocar3G
Home-page: https://github.com/hanback-lab/Autocar3G
Author: Hanback Electronics CO. Ltd. Research Insitutue
Author-email: lab@hanback.co.kr
Classifier: Programming Language :: Python :: 3
Classifier: License :: OSI Approved :: MIT License
Classifier: Operating System :: OS Independent
Requires-Python: >=3.8
Requires-Dist: paho-mqtt
Requires-Dist: tensorflow>=2.5.0
Requires-Dist: torch>=2.4.1
Dynamic: author
Dynamic: author-email
Dynamic: classifier
Dynamic: description
Dynamic: description-content-type
Dynamic: home-page
Dynamic: requires-dist
Dynamic: requires-python
Dynamic: summary
